CHANGES
COPYING
MANIFEST.in
MPL-2.0
README.md
setup.py
authheaders/__init__.py
authheaders/dmarc_lookup.py
authheaders/dmarcpolicyfind.py
authheaders/public_suffix_list.txt
authheaders.egg-info/PKG-INFO
authheaders.egg-info/SOURCES.txt
authheaders.egg-info/dependency_links.txt
authheaders.egg-info/entry_points.txt
authheaders.egg-info/not-zip-safe
authheaders.egg-info/requires.txt
authheaders.egg-info/top_level.txt
authheaders/test/test.bad.message
authheaders/test/test.gov.message
authheaders/test/test.message
authheaders/test/test.message_multi
authheaders/test/test.message_multi2
authheaders/test/test.message_np1
authheaders/test/test.message_np2
authheaders/test/test.message_signed
authheaders/test/test.message_sub
authheaders/test/test.nofrom.message
authheaders/test/test.private
authheaders/test/test.txt
authheaders/test/test_authentication.py
authheaders/test/test_nop.message
authheaders/test/testcomma.message