Metadata-Version: 2.1
Name: authheaders
Version: 0.16.2
Summary: A library wrapping email authentication header verification and generation.
Home-page: https://github.com/ValiMail/authentication-headers
Author: Gene Shuman
Author-email: gene@valimail.com
License: MIT
Keywords: email,headers,SPF,DKIM,DMARC,ARC
Platform: UNKNOWN
Classifier: Development Status :: 4 - Beta
Classifier: Topic :: Utilities
Classifier: License :: OSI Approved :: MIT License
Classifier: Natural Language :: English
Classifier: Operating System :: OS Independent
Classifier: Programming Language :: Python
Classifier: Programming Language :: Python :: 3
Classifier: Topic :: Communications :: Email :: Mail Transport Agents
Classifier: Topic :: Communications :: Email :: Filters
Classifier: Topic :: Software Development :: Libraries :: Python Modules
Requires-Python: >3.7
